qsqla/__init__.py
qsqla/query.py
qsqla-0.0.2.dist-info/DESCRIPTION.rst
qsqla-0.0.2.dist-info/METADATA
qsqla-0.0.2.dist-info/RECORD
qsqla-0.0.2.dist-info/WHEEL
qsqla-0.0.2.dist-info/metadata.json
qsqla-0.0.2.dist-info/top_level.txt
