Metadata-Version: 2.0
Name: qsqla
Version: 0.0.2
Summary: qSQLA is a query builder for SQLAlchemy Core Selectables 
Home-page: https://github.com/hoffmann/qsqla
Author: Peter Hoffmann
Author-email: peter.hoffmann@blue-yonder.com
License: BSD
Download-URL: https://github.com/hoffmann/qsqla/tarball/
Platform: UNKNOWN
Classifier: Development Status :: 3 - Alpha
Classifier: Intended Audience :: Developers
Classifier: Programming Language :: Python :: 3
Requires-Dist: python-dateutil
Requires-Dist: sqlalchemy
